app/__init__.py
app/agents/__init__.py
app/agents/agent.py
app/agents/prompts.py
app/main.py
app/server.py
app/utils/__init__.py
app/utils/directory_util.py
app/utils/gitignore_parser.py
app/utils/langchain_validation_util.py
app/utils/logging_utils.py
app/utils/print_tree_util.py
app/utils/version_util.py
pyproject.toml
scripts.py
templates/asset-manifest.json
templates/favicon.ico
templates/index.html
templates/static/css/main.8af23da0.css
templates/static/css/main.8af23da0.css.map
templates/static/js/main.ec0c6a2a.js
templates/static/js/main.ec0c6a2a.js.LICENSE.txt
templates/static/js/main.ec0c6a2a.js.map
templates/static/media/fa-brands-400.455ea818179b4def0c43.woff2
templates/static/media/fa-brands-400.60127e352b7a11f7f1bc.ttf
templates/static/media/fa-regular-400.21cb8f55d8e0c5b89751.woff2
templates/static/media/fa-regular-400.eb91f7b948a42799f678.ttf
templates/static/media/fa-solid-900.4d986b00ff9ca3828fbd.woff2
templates/static/media/fa-solid-900.bacd5de623fb563b961a.ttf
templates/static/media/fa-v4compatibility.c8e090db312b0bea2aa2.ttf
templates/static/media/fa-v4compatibility.cf7f5903d06b79ad60f1.woff2
spyziya-0.1.33.dist-info/LICENSE
spyziya-0.1.33.dist-info/METADATA
spyziya-0.1.33.dist-info/WHEEL
spyziya-0.1.33.dist-info/entry_points.txt
spyziya-0.1.33.dist-info/RECORD
