Metadata-Version: 2.1
Name: spyziya
Version: 0.1.33
Summary: 
Author: Vishnu Krishnaprasad
Author-email: vishnukool@gmail.com
Requires-Python: >=3.9,<4.0
Classifier: Programming Language :: Python :: 3
Classifier: Programming Language :: Python :: 3.9
Classifier: Programming Language :: Python :: 3.10
Classifier: Programming Language :: Python :: 3.11
Classifier: Programming Language :: Python :: 3.12
Requires-Dist: boto3 (>=1.34.88,<2.0.0)
Requires-Dist: jinja2 (>=3.1.3,<4.0.0)
Requires-Dist: langchain (>=0.1,<0.2)
Requires-Dist: langchain-anthropic (>=0.1.4,<0.2.0)
Requires-Dist: langchain-aws (>=0.1.0,<0.2.0)
Requires-Dist: langchain-cli (>=0.0.15)
Requires-Dist: langchainhub (>=0.1.15)
Requires-Dist: pydantic (<2)
Requires-Dist: pydevd-pycharm (>=241.15989.57,<242.0.0)
Requires-Dist: tiktoken (>=0.6.0,<0.7.0)
Requires-Dist: uvicorn (>=0.23.2,<0.24.0)
